calculatormharis/__init__.py
calculatormharis/api_helper.py
calculatormharis/calculatormharis_client.py
calculatormharis/configuration.py
calculatormharis/decorators.py
calculatormharis/controllers/__init__.py
calculatormharis/controllers/base_controller.py
calculatormharis/controllers/simple_calculator_controller.py
calculatormharis/exceptions/__init__.py
calculatormharis/exceptions/api_exception.py
calculatormharis/http/__init__.py
calculatormharis/http/http_call_back.py
calculatormharis/http/http_client.py
calculatormharis/http/http_method_enum.py
calculatormharis/http/http_request.py
calculatormharis/http/http_response.py
calculatormharis/http/requests_client.py
calculatormharis/models/__init__.py
calculatormharis/models/operation_type_enum.py
calculatormharis/utilities/__init__.py
calculatormharis/utilities/file_wrapper.py
tests/__init__.py
tests/http_response_catcher.py
tests/test_helper.py
tests/controllers/__init__.py
tests/controllers/controller_test_base.py
tests/controllers/test_simple_calculator_controller.py
apimaticcalculatortestapimatic-1.0.0.dist-info/LICENSE
apimaticcalculatortestapimatic-1.0.0.dist-info/METADATA
apimaticcalculatortestapimatic-1.0.0.dist-info/WHEEL
apimaticcalculatortestapimatic-1.0.0.dist-info/top_level.txt
apimaticcalculatortestapimatic-1.0.0.dist-info/RECORD
